restrained_ESP_fit/resp_wrapper.py
restrained_ESP_fit/build/resp
restrained_ESP_fit-2.4.1.dist-info/LICENSE.txt
restrained_ESP_fit-2.4.1.dist-info/METADATA
restrained_ESP_fit-2.4.1.dist-info/WHEEL
restrained_ESP_fit-2.4.1.dist-info/entry_points.txt
restrained_ESP_fit-2.4.1.dist-info/top_level.txt
restrained_ESP_fit-2.4.1.dist-info/RECORD
