Metadata-Version: 2.1
Name: restrained-ESP-fit
Version: 2.4.1
Summary: Fitting partial charges to molecular Electrostatic Potential field
Home-page: https://github.com/jszopi/restrained-ESP-fit
Maintainer: Jan Szopinski
Maintainer-email: jszopi@users.noreply.github.com
License: GPLv3
Keywords: restrained molecular electrostatic potential ESP fitting RESP atomic partial charges
Platform: UNKNOWN
Classifier: Development Status :: 3 - Alpha
Classifier: Environment :: Console
Classifier: Intended Audience :: Science/Research
Classifier: License :: OSI Approved :: GNU General Public License v3 (GPLv3)
Classifier: Operating System :: MacOS :: MacOS X
Classifier: Operating System :: POSIX :: Linux
Classifier: Programming Language :: Python :: 3
Classifier: Programming Language :: Python :: Implementation :: CPython
Classifier: Topic :: Scientific/Engineering :: Chemistry
Requires-Python: >=3
